BlueKumquatAutoDiff/__init__.py
BlueKumquatAutoDiff/autodiff.py
BlueKumquatAutoDiff/demo.py
BlueKumquatAutoDiff-1.0.0.dist-info/LICENSE
BlueKumquatAutoDiff-1.0.0.dist-info/METADATA
BlueKumquatAutoDiff-1.0.0.dist-info/WHEEL
BlueKumquatAutoDiff-1.0.0.dist-info/top_level.txt
BlueKumquatAutoDiff-1.0.0.dist-info/RECORD
