Metadata-Version: 2.1
Name: BlueKumquatAutoDiff
Version: 1.0.0
Summary: Package for Automatic Differentiation functions and objects
Home-page: https://github.com/cs107-blue-kumquat/cs107-FinalProject.git
Author: Jailyn Clark, Mason Burlage, Caitlin Lau, Lu Yu
Author-email: caitlinjlau@gmail.com
License: MIT
Keywords: Auto-diff
Platform: UNKNOWN
Classifier: Development Status :: 3 - Alpha
Classifier: Intended Audience :: Developers
Classifier: Topic :: Software Development :: Build Tools
Classifier: License :: OSI Approved :: MIT License
Classifier: Programming Language :: Python :: 3
Classifier: Programming Language :: Python :: 3.4
Classifier: Programming Language :: Python :: 3.5
Classifier: Programming Language :: Python :: 3.6
Classifier: Programming Language :: Python :: 3.7
Classifier: Programming Language :: Python :: 3.8
Requires-Dist: numpy
Requires-Dist: pytest
